{
  "heroes": [
    {
      "id": "b9370b82-5d66-4d78-a4f8-8ec97b4a2737",
      "name": "Superman",
      "description": "strong",
      "element": "earth"
    },
    {
      "id": "a4007de1-e3e8-4d62-8177-313ac3e0c9ad",
      "name": "Fierman",
      "description": "fier",
      "element": "fire"
    },
    {
      "id": "fb39c771-b743-4574-8d87-10b41edd1f92",
      "name": "Batman",
      "description": "fligh",
      "element": "wind"
    },
    {
      "id": "82d07650-92b1-456e-a51e-3b4397ab0ab9",
      "name": "Aquaman",
      "description": "water power",
      "element": "water"
    }
  ],
  "filters": [
    {
      "id": "all",
      "name": "all"
    },
    {
      "id": "fire",
      "name": "fire"
    },
    {
      "id": "water",
      "name": "water"
    },
    {
      "id": "wind",
      "name": "wind"
    },
    {
      "id": "earth",
      "name": "earth"
    }
  ]
}